cli/__init__.py
cli/main.py
mcp_hive_cli-0.1.4.dist-info/METADATA
mcp_hive_cli-0.1.4.dist-info/WHEEL
mcp_hive_cli-0.1.4.dist-info/entry_points.txt
mcp_hive_cli-0.1.4.dist-info/top_level.txt
mcp_hive_cli-0.1.4.dist-info/RECORD
