Metadata-Version: 2.2
Name: mcp-hive-cli
Version: 0.1.4
Summary: CLI tool for creating MCP agents
Home-page: https://github.com/trilogy-group/mcp-hive-app
Author: Ashish Mandal
Author-email: mandal.ashish@codenation.co.in
Classifier: Programming Language :: Python :: 3
Classifier: License :: OSI Approved :: MIT License
Classifier: Operating System :: OS Independent
Requires-Python: >=3.8
Requires-Dist: click>=8.0.0
Requires-Dist: pyyaml>=6.0
Requires-Dist: jinja2>=3.0.0
Requires-Dist: rich>=10.0.0
Requires-Dist: python-dotenv>=0.19.0
Requires-Dist: langchain-core>=0.1.0
Requires-Dist: langchain-anthropic>=0.1.0
Dynamic: author
Dynamic: author-email
Dynamic: classifier
Dynamic: description
Dynamic: description-content-type
Dynamic: home-page
Dynamic: requires-dist
Dynamic: requires-python
Dynamic: summary
